ili2c/__init__.py
ili2c/ili2c.py
ili2c/lib_ext/graal_isolate.h
ili2c/lib_ext/graal_isolate_dynamic.h
ili2c/lib_ext/libili2c.dll
ili2c/lib_ext/libili2c.h
ili2c/lib_ext/libili2c.lib
ili2c/lib_ext/libili2c_dynamic.h
ili2c/tests/__init__.py
ili2c/tests/test_ili2c.py
ili2c-0.0.7.dist-info/METADATA
ili2c-0.0.7.dist-info/WHEEL
ili2c-0.0.7.dist-info/top_level.txt
ili2c-0.0.7.dist-info/RECORD
