Metadata-Version: 2.1
Name: ili2c
Version: 0.0.7
Summary: Python package for ili2c.
Home-page: https://github.com/edigonzales/ili2c-node
Author: Stefan Ziegler
Author-email: edi.gonzales@gmail.com
License: MIT license
Keywords: ili2c,interlis
Classifier: Programming Language :: Python :: 3
Classifier: License :: OSI Approved :: MIT License
Classifier: Operating System :: POSIX :: Linux
Classifier: Operating System :: Microsoft :: Windows
Classifier: Operating System :: MacOS
Requires-Python: >=3.8
Requires-Dist: importlib-resources
Provides-Extra: test
Requires-Dist: pytest; extra == "test"
